pythonProject1/__init__.py
pythonProject1/main.py
pythonProject1/test.py
zctest-0.0.1.dist-info/METADATA
zctest-0.0.1.dist-info/WHEEL
zctest-0.0.1.dist-info/top_level.txt
zctest-0.0.1.dist-info/RECORD
