Metadata-Version: 2.1
Name: zctest
Version: 0.0.1
Summary: An example Python package
Home-page: UNKNOWN
Author: onechorm
Author-email: zconechorm@163.com
License: MIT
Platform: UNKNOWN
Requires-Dist: numpy
Requires-Dist: pandas
